examples/__init__.py
examples/generated_program.py
pyautoeasy/__init__.py
pyautoeasy/__main__.py
pyautoeasy/cli.py
pyautoeasy/locate_points.py
pyautoeasy/sample.py
pyautoeasy/screen_point.py
pyautoeasy/examples/__init__.py
pyautoeasy/examples/generated_program.py
pyautoeasy-0.0.5.dist-info/LICENSE
pyautoeasy-0.0.5.dist-info/METADATA
pyautoeasy-0.0.5.dist-info/WHEEL
pyautoeasy-0.0.5.dist-info/entry_points.txt
pyautoeasy-0.0.5.dist-info/top_level.txt
pyautoeasy-0.0.5.dist-info/RECORD
