Metadata-Version: 2.1
Name: pyautoeasy
Version: 0.0.5
Summary: A simple GUI automation tool to automate your boring tasks
Home-page: UNKNOWN
Author: Dingu Sagar
Author-email: <dingusagar@gmail.com>
License: UNKNOWN
Keywords: python,pyautoeasy,pyautogui,automate gui,automate ui,ui automation
Platform: UNKNOWN
Classifier: Development Status :: 3 - Alpha
Classifier: Intended Audience :: Developers
Classifier: Programming Language :: Python :: 3
Classifier: Operating System :: Unix
Classifier: Operating System :: MacOS :: MacOS X
Classifier: Operating System :: Microsoft :: Windows
Requires-Dist: PyAutoGUI (==0.9.53)
Requires-Dist: pynput (==1.7.3)
Requires-Dist: tabulate (==0.8.9)
